SteamFactory-0.1.dist-info/DESCRIPTION.rst
SteamFactory-0.1.dist-info/METADATA
SteamFactory-0.1.dist-info/RECORD
SteamFactory-0.1.dist-info/WHEEL
SteamFactory-0.1.dist-info/metadata.json
SteamFactory-0.1.dist-info/top_level.txt
steamfactory/__init__.py
steamfactory/core.py
