Metadata-Version: 2.0
Name: SteamFactory
Version: 0.1
Summary: Replacement for multiprocessing.Pool.
Home-page: https://github.com/rshk/steamfactory
Author: Samuele Santi
Author-email: samuele@samuelesanti.com
License: BSD License
Platform: UNKNOWN
Classifier: License :: OSI Approved :: BSD License
Classifier: Programming Language :: Python :: 3.4
Classifier: Programming Language :: Python :: 3.5
